virtool_core/__init__.py
virtool_core/bio.py
virtool_core/errors.py
virtool_core/logging.py
virtool_core/models/__init__.py
virtool_core/models/account.py
virtool_core/models/administrator.py
virtool_core/models/analysis.py
virtool_core/models/auth.py
virtool_core/models/basemodel.py
virtool_core/models/blast.py
virtool_core/models/enums.py
virtool_core/models/genbank.py
virtool_core/models/group.py
virtool_core/models/group_minimal.py
virtool_core/models/history.py
virtool_core/models/hmm.py
virtool_core/models/index.py
virtool_core/models/instancemessage.py
virtool_core/models/job.py
virtool_core/models/label.py
virtool_core/models/ml.py
virtool_core/models/otu.py
virtool_core/models/project.py
virtool_core/models/reference.py
virtool_core/models/roles.py
virtool_core/models/sample_base.py
virtool_core/models/samples.py
virtool_core/models/searchresult.py
virtool_core/models/session.py
virtool_core/models/settings.py
virtool_core/models/spaces.py
virtool_core/models/subtraction.py
virtool_core/models/task.py
virtool_core/models/upload.py
virtool_core/models/user.py
virtool_core/models/user_base.py
virtool_core/models/validators.py
virtool_core/mongo.py
virtool_core/py.typed
virtool_core/redis.py
virtool_core/utils.py
virtool_core-15.0.1.dist-info/LICENSE
virtool_core-15.0.1.dist-info/METADATA
virtool_core-15.0.1.dist-info/WHEEL
virtool_core-15.0.1.dist-info/RECORD
