Metadata-Version: 2.3
Name: virtool-core
Version: 15.0.1
Summary: Core utilities for Virtool.
License: MIT
Author: Ian Boyes
Requires-Python: >=3.12,<3.13
Classifier: License :: OSI Approved :: MIT License
Classifier: Programming Language :: Python :: 3
Classifier: Programming Language :: Python :: 3.12
Classifier: Topic :: Software Development :: Libraries
Requires-Dist: arrow (>=1.2.2,<2.0.0)
Requires-Dist: dictdiffer (>=0.9.0,<0.10.0)
Requires-Dist: email-validator (>=2.2.0,<3.0.0)
Requires-Dist: enum-tools (>=0.11.0,<0.12.0)
Requires-Dist: motor (>=3.6.0,<4.0.0)
Requires-Dist: orjson (>=3.10.11,<4.0.0)
Requires-Dist: pydantic (>=2.9.2,<3.0.0)
Requires-Dist: redis[hiredis] (>=5.2.0,<6.0.0)
Requires-Dist: structlog (>=24.4.0,<25.0.0)
Project-URL: Repository, https://github.com/virtool/virtool-core
